Metadata-Version: 2.1
Name: adafruit-circuitpython-pypixelbuf
Version: 2.2.7
Summary: Pure python implementation of _pixelbuf for smaller boards.
Home-page: https://github.com/adafruit/Adafruit_CircuitPython_Pypixelbuf
Author: Roy Hooper
Author-email: rhooper@toybox.ca
License: MIT
Keywords: adafruit blinka circuitpython micropython pypixelbuf pypixelbuf pixelbuf led
Platform: UNKNOWN
Classifier: Development Status :: 3 - Alpha
Classifier: Intended Audience :: Developers
Classifier: Topic :: Software Development :: Libraries
Classifier: Topic :: System :: Hardware
Classifier: License :: OSI Approved :: MIT License
Classifier: Programming Language :: Python :: 3
Classifier: Programming Language :: Python :: 3.4
Classifier: Programming Language :: Python :: 3.5
License-File: LICENSE
